LICENSE
README.md
setup.py
src/py_mongo_backup_restore/__init__.py
src/py_mongo_backup_restore/main.py
src/py_mongo_backup_restore.egg-info/PKG-INFO
src/py_mongo_backup_restore.egg-info/SOURCES.txt
src/py_mongo_backup_restore.egg-info/dependency_links.txt
src/py_mongo_backup_restore.egg-info/top_level.txt