Metadata-Version: 2.1
Name: py-mongo-backup-restore
Version: 2.0.0
Summary: Python Library to Backup and Restore MongoDB
Home-page: https://github.com/sannjayy/py-mongo-backup-restore
Author: Sanjay Sikdar
Author-email: me@sanjaysikdar.dev
License: MIT
Project-URL: Bug Reports, https://github.com/sannjayy/py-mongo-backup-restore/issues
Project-URL: Funding, https://www.paypal.com/paypalme/znasofficial
Project-URL: Say Thanks!, https://saythanks.io/to/sannjayy
Project-URL: Source, https://github.com/sannjayy/py-mongo-backup-restore/
Keywords: python,mongo,backup,restore,mongodb
Classifier: Development Status :: 5 - Production/Stable
Classifier: Intended Audience :: Developers
Classifier: Topic :: Software Development :: Libraries :: Python Modules
Classifier: Operating System :: OS Independent
Classifier: License :: OSI Approved :: MIT License
Classifier: Programming Language :: Python :: 3.10
Classifier: Programming Language :: Python :: 3.11
Classifier: Programming Language :: Python :: 3.12
Requires-Python: >=3.10, <4
License-File: LICENSE
